rokka_client_codegen/__init__.py
rokka_client_codegen/api_client.py
rokka_client_codegen/configuration.py
rokka_client_codegen/rest.py
rokka_client_codegen/api/__init__.py
rokka_client_codegen/api/admin_api.py
rokka_client_codegen/api/sourceimages_api.py
rokka_client_codegen/api/stacks_api.py
rokka_client_codegen/models/__init__.py
rokka_client_codegen/models/inline_response200.py
rokka_client_codegen/models/list_source_images_response.py
rokka_client_codegen/models/list_stacks_response.py
rokka_client_codegen/models/list_user_memberships_response.py
rokka_client_codegen/models/membership.py
rokka_client_codegen/models/organization.py
rokka_client_codegen/models/organization_definition.py
rokka_client_codegen/models/organization_limit.py
rokka_client_codegen/models/organization_options.py
rokka_client_codegen/models/role.py
rokka_client_codegen/models/roles.py
rokka_client_codegen/models/source_image.py
rokka_client_codegen/models/stack.py
rokka_client_codegen/models/stack_definition.py
rokka_client_codegen/models/stack_expression.py
rokka_client_codegen/models/stack_expression_overrides.py
rokka_client_codegen/models/stack_operation.py
rokka_client_codegen/models/stack_operation_description.py
rokka_client_codegen/models/stack_operation_description_properties.py
rokka_client_codegen/models/stack_options.py
rokka_client_codegen/models/user.py
rokka_client_codegen/models/user_definition.py
rokka_client_codegen/models/user_membership.py
test/__init__.py
test/test_admin_api.py
test/test_inline_response200.py
test/test_list_source_images_response.py
test/test_list_stacks_response.py
test/test_list_user_memberships_response.py
test/test_membership.py
test/test_organization.py
test/test_organization_definition.py
test/test_organization_limit.py
test/test_organization_options.py
test/test_role.py
test/test_roles.py
test/test_source_image.py
test/test_sourceimages_api.py
test/test_stack.py
test/test_stack_definition.py
test/test_stack_expression.py
rokka_client_codegen-0.2.0.dist-info/LICENSE.txt
rokka_client_codegen-0.2.0.dist-info/METADATA
rokka_client_codegen-0.2.0.dist-info/WHEEL
rokka_client_codegen-0.2.0.dist-info/top_level.txt
rokka_client_codegen-0.2.0.dist-info/RECORD
