Metadata-Version: 2.1
Name: rokka-client-codegen
Version: 0.2.0
Summary: Client for rokka.io
Home-page: https://github.com/rokka-io/rokka-python-codegen
Author: rokka
Author-email: rokka@rokka.io
License: MIT
Keywords: rokka.io,rokka
Platform: UNKNOWN
Classifier: Development Status :: 4 - Beta
Classifier: License :: OSI Approved :: MIT License
Requires-Dist: certifi (>=2017.4.17)
Requires-Dist: python-dateutil (>=2.1)
Requires-Dist: six (>=1.10)
Requires-Dist: urllib3 (>=1.23)
